b8tex/__init__.py
b8tex/api.py
b8tex/cli.py
b8tex/exceptions.py
b8tex/py.typed
b8tex/core/__init__.py
b8tex/core/binary.py
b8tex/core/cache.py
b8tex/core/config.py
b8tex/core/diagnostics.py
b8tex/core/document.py
b8tex/core/options.py
b8tex/core/project.py
b8tex/core/results.py
b8tex/core/retry.py
b8tex/core/runner.py
b8tex/core/timeouts.py
b8tex/core/validation.py
b8tex/core/watcher.py
b8tex/core/workspace.py
b8tex/templates/__init__.py
b8tex/templates/api.py
b8tex/templates/builder.py
b8tex/templates/config.py
b8tex/templates/data.py
b8tex/templates/document.py
b8tex/templates/escape.py
b8tex/templates/renderer.py
b8tex/templates/validation.py
b8tex/templates/styles/STYLE_CONTRACTS.md
b8tex/templates/styles/acl.sty
b8tex/templates/styles/iclr.sty
b8tex/templates/styles/neurips.sty
b8tex/utils/__init__.py
b8tex-0.2.1.dist-info/METADATA
b8tex-0.2.1.dist-info/WHEEL
b8tex-0.2.1.dist-info/entry_points.txt
b8tex-0.2.1.dist-info/licenses/LICENSE
b8tex-0.2.1.dist-info/RECORD
