Metadata-Version: 2.4
Name: b8tex
Version: 0.2.1
Summary: A high-level Python wrapper for Tectonic LaTeX compiler with project-aware compilation
Project-URL: Homepage, https://github.com/samehkamaleldin/pytex
Project-URL: Documentation, https://github.com/samehkamaleldin/pytex#readme
Project-URL: Repository, https://github.com/samehkamaleldin/pytex
Project-URL: Issues, https://github.com/samehkamaleldin/pytex/issues
Author-email: Sameh Mohamed <sameh.kamaleldin@gmail.com>
License: MIT
License-File: LICENSE
Keywords: compiler,latex,pdf,tectonic,typesetting
Classifier: Development Status :: 3 - Alpha
Classifier: Intended Audience :: Developers
Classifier: Intended Audience :: Science/Research
Classifier: License :: OSI Approved :: MIT License
Classifier: Operating System :: OS Independent
Classifier: Programming Language :: Python :: 3
Classifier: Programming Language :: Python :: 3.13
Classifier: Topic :: Software Development :: Libraries :: Python Modules
Classifier: Topic :: Text Processing :: Markup :: LaTeX
Classifier: Typing :: Typed
Requires-Python: >=3.13
Requires-Dist: jinja2>=3.1.0
Requires-Dist: platformdirs>=4.0.0
Requires-Dist: tomli>=2.0.0; python_version < '3.11'
Requires-Dist: typing-extensions>=4.12.0
Provides-Extra: async
Requires-Dist: anyio>=4.7.0; extra == 'async'
Provides-Extra: dev
Requires-Dist: mypy>=1.13.0; extra == 'dev'
Requires-Dist: pytest-asyncio>=0.24.0; extra == 'dev'
Requires-Dist: pytest-cov>=6.0.0; extra == 'dev'
Requires-Dist: pytest>=8.3.0; extra == 'dev'
Requires-Dist: ruff>=0.8.0; extra == 'dev'
Provides-Extra: templates
Requires-Dist: matplotlib>=3.7.0; extra == 'templates'
Requires-Dist: pandas>=2.0.0; extra == 'templates'
Provides-Extra: watch
Requires-Dist: watchfiles>=0.24.0; extra == 'watch'
